{
  "AWSTemplateFormatVersion": "2010-09-09",
  "Description": "{\"createdOn\":\"Windows\",\"createdBy\":\"Amplify\",\"createdWith\":\"7.6.12\",\"stackType\":\"function-Lambda\",\"metadata\":{}}",
  "Parameters": {
    "CloudWatchRule": {
      "Type": "String",
      "Default": "NONE",
      "Description": " Schedule Expression"
    },
    "deploymentBucketName": {
      "Type": "String"
    },
    "env": {
      "Type": "String"
    },
    "s3Key": {
      "Type": "String"
    },
    "apitapgiveschallengeGraphQLAPIIdOutput": {
      "Type": "String",
      "Default": "apitapgiveschallengeGraphQLAPIIdOutput"
    },
    "apitapgiveschallengeGraphQLAPIEndpointOutput": {
      "Type": "String",
      "Default": "apitapgiveschallengeGraphQLAPIEndpointOutput"
    },
    "storagehistoryBucketName": {
      "Type": "String",
      "Default": "storagehistoryBucketName"
    }
  },
  "Conditions": {
    "ShouldNotCreateEnvResources": {
      "Fn::Equals": [
        {
          "Ref": "env"
        },
        "NONE"
      ]
    }
  },
  "Resources": {
    "LambdaFunction": {
      "Type": "AWS::Lambda::Function",
      "Metadata": {
        "aws:asset:path": "./src",
        "aws:asset:property": "Code"
      },
      "Properties": {
        "Code": {
          "S3Bucket": {
            "Ref": "deploymentBucketName"
          },
          "S3Key": {
            "Ref": "s3Key"
          }
        },
        "Handler": "index.handler",
        "FunctionName": {
          "Fn::If": [
            "ShouldNotCreateEnvResources",
            "historyfunction",
            {
              "Fn::Join": [
                "",
                [
                  "historyfunction",
                  "-",
                  {
                    "Ref": "env"
                  }
                ]
              ]
            }
          ]
        },
        "Environment": {
          "Variables": {
            "ENV": {
              "Ref": "env"
            },
            "REGION": {
              "Ref": "AWS::Region"
            },
            "API_TAPGIVESCHALLENGE_GRAPHQLAPIIDOUTPUT": {
              "Ref": "apitapgiveschallengeGraphQLAPIIdOutput"
            },
            "API_TAPGIVESCHALLENGE_GRAPHQLAPIENDPOINTOUTPUT": {
              "Ref": "apitapgiveschallengeGraphQLAPIEndpointOutput"
            },
            "STORAGE_HISTORY_BUCKETNAME": {
              "Ref": "storagehistoryBucketName"
            },
            "API_TAPGIVESCHALLENGE_SITETABLE_NAME": {
              "Fn::ImportValue": {
                "Fn::Sub": "${apitapgiveschallengeGraphQLAPIIdOutput}:GetAtt:SiteTable:Name"
              }
            },
            "API_TAPGIVESCHALLENGE_SITETABLE_ARN": {
              "Fn::Join": [
                "",
                [
                  "arn:aws:dynamodb:",
                  {
                    "Ref": "AWS::Region"
                  },
                  ":",
                  {
                    "Ref": "AWS::AccountId"
                  },
                  ":table/",
                  {
                    "Fn::ImportValue": {
                      "Fn::Sub": "${apitapgiveschallengeGraphQLAPIIdOutput}:GetAtt:SiteTable:Name"
                    }
                  }
                ]
              ]
            }
          }
        },
        "Role": {
          "Fn::GetAtt": [
            "LambdaExecutionRole",
            "Arn"
          ]
        },
        "Runtime": "nodejs14.x",
        "Layers": [],
        "Timeout": 25
      }
    },
    "LambdaExecutionRole": {
      "Type": "AWS::IAM::Role",
      "Properties": {
        "RoleName": {
          "Fn::If": [
            "ShouldNotCreateEnvResources",
            "tapgiveschallengeLambdaRole3dc877e8",
            {
              "Fn::Join": [
                "",
                [
                  "tapgiveschallengeLambdaRole3dc877e8",
                  "-",
                  {
                    "Ref": "env"
                  }
                ]
              ]
            }
          ]
        },
        "AssumeRolePolicyDocument": {
          "Version": "2012-10-17",
          "Statement": [
            {
              "Effect": "Allow",
              "Principal": {
                "Service": [
                  "lambda.amazonaws.com"
                ]
              },
              "Action": [
                "sts:AssumeRole"
              ]
            }
          ]
        }
      }
    },
    "lambdaexecutionpolicy": {
      "DependsOn": [
        "LambdaExecutionRole"
      ],
      "Type": "AWS::IAM::Policy",
      "Properties": {
        "PolicyName": "lambda-execution-policy",
        "Roles": [
          {
            "Ref": "LambdaExecutionRole"
          }
        ],
        "PolicyDocument": {
          "Version": "2012-10-17",
          "Statement": [
            {
              "Effect": "Allow",
              "Action": [
                "logs:CreateLogGroup",
                "logs:CreateLogStream",
                "logs:PutLogEvents"
              ],
              "Resource": {
                "Fn::Sub": [
                  "arn:aws:logs:${region}:${account}:log-group:/aws/lambda/${lambda}:log-stream:*",
                  {
                    "region": {
                      "Ref": "AWS::Region"
                    },
                    "account": {
                      "Ref": "AWS::AccountId"
                    },
                    "lambda": {
                      "Ref": "LambdaFunction"
                    }
                  }
                ]
              }
            }
          ]
        }
      }
    },
    "AmplifyResourcesPolicy": {
      "DependsOn": [
        "LambdaExecutionRole"
      ],
      "Type": "AWS::IAM::Policy",
      "Properties": {
        "PolicyName": "amplify-lambda-execution-policy",
        "Roles": [
          {
            "Ref": "LambdaExecutionRole"
          }
        ],
        "PolicyDocument": {
          "Version": "2012-10-17",
          "Statement": [
            {
              "Effect": "Allow",
              "Action": [
                "appsync:GraphQL"
              ],
              "Resource": [
                {
                  "Fn::Join": [
                    "",
                    [
                      "arn:aws:appsync:",
                      {
                        "Ref": "AWS::Region"
                      },
                      ":",
                      {
                        "Ref": "AWS::AccountId"
                      },
                      ":apis/",
                      {
                        "Ref": "apitapgiveschallengeGraphQLAPIIdOutput"
                      },
                      "/types/Query/*"
                    ]
                  ]
                },
                {
                  "Fn::Join": [
                    "",
                    [
                      "arn:aws:appsync:",
                      {
                        "Ref": "AWS::Region"
                      },
                      ":",
                      {
                        "Ref": "AWS::AccountId"
                      },
                      ":apis/",
                      {
                        "Ref": "apitapgiveschallengeGraphQLAPIIdOutput"
                      },
                      "/types/Mutation/*"
                    ]
                  ]
                },
                {
                  "Fn::Join": [
                    "",
                    [
                      "arn:aws:appsync:",
                      {
                        "Ref": "AWS::Region"
                      },
                      ":",
                      {
                        "Ref": "AWS::AccountId"
                      },
                      ":apis/",
                      {
                        "Ref": "apitapgiveschallengeGraphQLAPIIdOutput"
                      },
                      "/types/Subscription/*"
                    ]
                  ]
                }
              ]
            },
            {
              "Effect": "Allow",
              "Action": "s3:ListBucket",
              "Resource": [
                {
                  "Fn::Join": [
                    "",
                    [
                      "arn:aws:s3:::",
                      {
                        "Ref": "storagehistoryBucketName"
                      }
                    ]
                  ]
                }
              ]
            },
            {
              "Effect": "Allow",
              "Action": [
                "s3:PutObject",
                "s3:GetObject",
                "s3:DeleteObject"
              ],
              "Resource": [
                {
                  "Fn::Join": [
                    "",
                    [
                      "arn:aws:s3:::",
                      {
                        "Ref": "storagehistoryBucketName"
                      },
                      "/*"
                    ]
                  ]
                }
              ]
            },
            {
              "Effect": "Allow",
              "Action": [
                "dynamodb:Put*",
                "dynamodb:Create*",
                "dynamodb:BatchWriteItem",
                "dynamodb:Get*",
                "dynamodb:BatchGetItem",
                "dynamodb:List*",
                "dynamodb:Describe*",
                "dynamodb:Scan",
                "dynamodb:Query",
                "dynamodb:Update*",
                "dynamodb:RestoreTable*",
                "dynamodb:Delete*"
              ],
              "Resource": [
                {
                  "Fn::Join": [
                    "",
                    [
                      "arn:aws:dynamodb:",
                      {
                        "Ref": "AWS::Region"
                      },
                      ":",
                      {
                        "Ref": "AWS::AccountId"
                      },
                      ":table/",
                      {
                        "Fn::ImportValue": {
                          "Fn::Sub": "${apitapgiveschallengeGraphQLAPIIdOutput}:GetAtt:SiteTable:Name"
                        }
                      }
                    ]
                  ]
                },
                {
                  "Fn::Join": [
                    "",
                    [
                      "arn:aws:dynamodb:",
                      {
                        "Ref": "AWS::Region"
                      },
                      ":",
                      {
                        "Ref": "AWS::AccountId"
                      },
                      ":table/",
                      {
                        "Fn::ImportValue": {
                          "Fn::Sub": "${apitapgiveschallengeGraphQLAPIIdOutput}:GetAtt:SiteTable:Name"
                        }
                      },
                      "/index/*"
                    ]
                  ]
                }
              ]
            }
          ]
        }
      }
    },
    "LambdaTriggerPolicyCustomerTransactions": {
      "DependsOn": [
        "LambdaExecutionRole"
      ],
      "Type": "AWS::IAM::Policy",
      "Properties": {
        "PolicyName": "amplify-lambda-execution-policy-CustomerTransactions",
        "Roles": [
          {
            "Ref": "LambdaExecutionRole"
          }
        ],
        "PolicyDocument": {
          "Version": "2012-10-17",
          "Statement": [
            {
              "Effect": "Allow",
              "Action": [
                "dynamodb:DescribeStream",
                "dynamodb:GetRecords",
                "dynamodb:GetShardIterator",
                "dynamodb:ListStreams"
              ],
              "Resource": {
                "Fn::ImportValue": {
                  "Fn::Sub": "${apitapgiveschallengeGraphQLAPIIdOutput}:GetAtt:CustomerTransactionsTable:StreamArn"
                }
              }
            }
          ]
        }
      }
    },
    "LambdaEventSourceMappingCustomerTransactions": {
      "Type": "AWS::Lambda::EventSourceMapping",
      "DependsOn": [
        "LambdaTriggerPolicyCustomerTransactions",
        "LambdaExecutionRole"
      ],
      "Properties": {
        "BatchSize": 100,
        "Enabled": true,
        "EventSourceArn": {
          "Fn::ImportValue": {
            "Fn::Sub": "${apitapgiveschallengeGraphQLAPIIdOutput}:GetAtt:CustomerTransactionsTable:StreamArn"
          }
        },
        "FunctionName": {
          "Fn::GetAtt": [
            "LambdaFunction",
            "Arn"
          ]
        },
        "StartingPosition": "LATEST"
      }
    },
    "CustomLambdaExecutionPolicy": {
      "Type": "AWS::IAM::Policy",
      "Properties": {
        "PolicyName": "custom-lambda-execution-policy",
        "PolicyDocument": {
          "Version": "2012-10-17",
          "Statement": [
            {
              "Action": [
                "firehose:*"
              ],
              "Effect": "Allow",
              "Resource": [
                "*"
              ]
            }
          ]
        },
        "Roles": [
          {
            "Ref": "LambdaExecutionRole"
          }
        ]
      },
      "DependsOn": "LambdaExecutionRole"
    }
  },
  "Outputs": {
    "Name": {
      "Value": {
        "Ref": "LambdaFunction"
      }
    },
    "Arn": {
      "Value": {
        "Fn::GetAtt": [
          "LambdaFunction",
          "Arn"
        ]
      }
    },
    "Region": {
      "Value": {
        "Ref": "AWS::Region"
      }
    },
    "LambdaExecutionRole": {
      "Value": {
        "Ref": "LambdaExecutionRole"
      }
    }
  }
}